[
    {
        "id": 1,
        "content": [
            {
                "type": "table",
                "content": [
                    {
                        "Name": "Adair",
                        "I.D.": "Christopher M.",
                        "Sex": 22070,
                        "Birth Date": "M",
                        "Age": "[X] 1978",
                        "Employee Type": 41.0,
                        "Employee": "Peace Officer",
                        "Instructor": "[X]",
                        "Supervisor": "[ ]"
                    },
                    {
                        "Name": "Adame",
                        "I.D.": "Jesse A.",
                        "Sex": 25042,
                        "Birth Date": "M",
                        "Age": "[X] 1988",
                        "Employee Type": 31.0,
                        "Employee": "Peace Officer",
                        "Instructor": "[X]",
                        "Supervisor": "[ ]"
                    },
                    {
                        "Name": "Adams",
                        "I.D.": "Ashley A.",
                        "Sex": 25657,
                        "Birth Date": "F",
                        "Age": "[X] -1990",
                        "Employee Type": 28.0,
                        "Employee": "Detention & Correction",
                        "Instructor": "[X]",
                        "Supervisor": "[ ]"
                    },
                    {
                        "Name": "Adams",
                        "I.D.": "Jeremiah A.",
                        "Sex": 20885,
                        "Birth Date": "M",
                        "Age": "[X] 1984",
                        "Employee Type": 35.0,
                        "Employee": "Peace Officer",
                        "Instructor": "[X]",
                        "Supervisor": "[ ]"
                    },
                    {
                        "Name": "Adams",
                        "I.D.": "Ross E.",
                        "Sex": 12,
                        "Birth Date": "M",
                        "Age": "[X] 1960",
                        "Employee Type": 59.0,
                        "Employee": "Peace Officer",
                        "Instructor": "[X]",
                        "Supervisor": "[ ]"
                    },
                    {
                        "Name": "Adams",
                        "I.D.": "Seth H.",
                        "Sex": 22864,
                        "Birth Date": "M",
                        "Age": "[X] 1989",
                        "Employee Type": 30.0,
                        "Employee": "Peace Officer",
                        "Instructor": "[X]",
                        "Supervisor": "[ ]"
                    },
                    {
                        "Name": "Adams",
                        "I.D.": "Tyler",
                        "Sex": 23612,
                        "Birth Date": "M",
                        "Age": "-1984",
                        "Employee Type": 34.0,
                        "Employee": "Detention & Correction",
                        "Instructor": "[X]",
                        "Supervisor": "[ ]"
                    },
                    {
                        "Name": "Adkins",
                        "I.D.": "Kevin",
                        "Sex": 16759,
                        "Birth Date": NaN,
                        "Age": NaN,
                        "Employee Type": NaN,
                        "Employee": "Peace Officer",
                        "Instructor": "[X]",
                        "Supervisor": "[ ]"
                    },
                    {
                        "Name": "Adolph",
                        "I.D.": "Jerry O.",
                        "Sex": 14668,
                        "Birth Date": "M",
                        "Age": "-1959",
                        "Employee Type": 59.0,
                        "Employee": "Detention & Correction",
                        "Instructor": "[X]",
                        "Supervisor": "[ ]"
                    },
                    {
                        "Name": "Adorni",
                        "I.D.": "Larry F.",
                        "Sex": 16753,
                        "Birth Date": "M",
                        "Age": "1957",
                        "Employee Type": 62.0,
                        "Employee": "Peace Officer",
                        "Instructor": "[X]",
                        "Supervisor": "[ ]"
                    },
                    {
                        "Name": "Adsem",
                        "I.D.": "Steven J.",
                        "Sex": 5552,
                        "Birth Date": "M",
                        "Age": "[ ] 1965",
                        "Employee Type": 54.0,
                        "Employee": "Peace Officer",
                        "Instructor": "[X]",
                        "Supervisor": "[ ]"
                    },
                    {
                        "Name": "Aggers",
                        "I.D.": "Mary",
                        "Sex": 12393,
                        "Birth Date": "F",
                        "Age": "[ ] 1970",
                        "Employee Type": 49.0,
                        "Employee": "Probation & Parole",
                        "Instructor": "[X]",
                        "Supervisor": "[ ]"
                    },
                    {
                        "Name": "Ahlin",
                        "I.D.": "Benjamin J.",
                        "Sex": 24854,
                        "Birth Date": "M",
                        "Age": "[ ] 1993",
                        "Employee Type": 26.0,
                        "Employee": "Detention & Correction",
                        "Instructor": "[X]",
                        "Supervisor": "[ ]"
                    },
                    {
                        "Name": "Ahmann",
                        "I.D.": "Jacob G.",
                        "Sex": 23943,
                        "Birth Date": "M",
                        "Age": "[ ] 1992",
                        "Employee Type": 27.0,
                        "Employee": "Peace Officer",
                        "Instructor": "[X]",
                        "Supervisor": "[ ]"
                    },
                    {
                        "Name": "Aiello",
                        "I.D.": "Antonio D.",
                        "Sex": 23659,
                        "Birth Date": "M",
                        "Age": "[ ] 1984",
                        "Employee Type": 35.0,
                        "Employee": "Detention & Correction",
                        "Instructor": "[X]",
                        "Supervisor": "[ ]"
                    },
                    {
                        "Name": "Albright",
                        "I.D.": "Christopher B.",
                        "Sex": 10496,
                        "Birth Date": "M",
                        "Age": "[ ] 1970",
                        "Employee Type": 49.0,
                        "Employee": "Peace Officer",
                        "Instructor": "[X]",
                        "Supervisor": "[ ]"
                    },
                    {
                        "Name": "Albright",
                        "I.D.": "Cody J.",
                        "Sex": 21589,
                        "Birth Date": "M",
                        "Age": "[ ] 1990",
                        "Employee Type": 29.0,
                        "Employee": "Detention & Correction",
                        "Instructor": "[X]",
                        "Supervisor": "[ ]"
                    },
                    {
                        "Name": "Aliperto",
                        "I.D.": "Benjamin J.",
                        "Sex": 25733,
                        "Birth Date": "M",
                        "Age": "[ ] 1995",
                        "Employee Type": 24.0,
                        "Employee": "Detention & Correction",
                        "Instructor": "[X]",
                        "Supervisor": "[ ]"
                    },
                    {
                        "Name": "Allen",
                        "I.D.": "Darin C.",
                        "Sex": 15463,
                        "Birth Date": "M",
                        "Age": "1974",
                        "Employee Type": 45.0,
                        "Employee": "Probation & Parole",
                        "Instructor": "[X]",
                        "Supervisor": "[ ]"
                    },
                    {
                        "Name": "Allen",
                        "I.D.": "Jack E.",
                        "Sex": 25,
                        "Birth Date": "M",
                        "Age": "-1959",
                        "Employee Type": 59.0,
                        "Employee": "Peace Officer",
                        "Instructor": "[X]",
                        "Supervisor": "[ ]"
                    },
                    {
                        "Name": "Allen",
                        "I.D.": "Jesse C.",
                        "Sex": 21937,
                        "Birth Date": "M",
                        "Age": "[ ] 1982",
                        "Employee Type": 37.0,
                        "Employee": "Peace Officer",
                        "Instructor": "[X]",
                        "Supervisor": "[ ]"
                    },
                    {
                        "Name": "Allen",
                        "I.D.": "Payton E.",
                        "Sex": 25919,
                        "Birth Date": "M",
                        "Age": "1999",
                        "Employee Type": 20.0,
                        "Employee": "Detention & Correction",
                        "Instructor": "[X]",
                        "Supervisor": "[ ]"
                    },
                    {
                        "Name": "Allen",
                        "I.D.": "Robert J.",
                        "Sex": 25593,
                        "Birth Date": "M",
                        "Age": "[ ] 1976",
                        "Employee Type": 43.0,
                        "Employee": "Peace Officer",
                        "Instructor": "[X]",
                        "Supervisor": "[ ]"
                    },
                    {
                        "Name": "Allen",
                        "I.D.": "Sean C.",
                        "Sex": 24063,
                        "Birth Date": "M",
                        "Age": "[ ] -1986",
                        "Employee Type": 32.0,
                        "Employee": "Peace Officer",
                        "Instructor": "[X]",
                        "Supervisor": "[ ]"
                    },
                    {
                        "Name": "Allen",
                        "I.D.": "Tammy A.",
                        "Sex": 17266,
                        "Birth Date": NaN,
                        "Age": "-1967",
                        "Employee Type": 51.0,
                        "Employee": "Detention & Correction",
                        "Instructor": "[X]",
                        "Supervisor": "[ ]"
                    },
                    {
                        "Name": "Allison",
                        "I.D.": "Derek",
                        "Sex": 25076,
                        "Birth Date": "M",
                        "Age": "1999",
                        "Employee Type": 20.0,
                        "Employee": "Detention & Correction",
                        "Instructor": "[X]",
                        "Supervisor": "[ ]"
                    },
                    {
                        "Name": "Allison",
                        "I.D.": "Thomas B.",
                        "Sex": 22103,
                        "Birth Date": "M",
                        "Age": "-1992",
                        "Employee Type": 26.0,
                        "Employee": "Peace Officer",
                        "Instructor": "[X]",
                        "Supervisor": "[ ]"
                    },
                    {
                        "Name": "Allmendinger",
                        "I.D.": "Jacob O.",
                        "Sex": 20851,
                        "Birth Date": "M",
                        "Age": "-1987",
                        "Employee Type": 31.0,
                        "Employee": "Peace Officer",
                        "Instructor": "[X]",
                        "Supervisor": "[ ]"
                    },
                    {
                        "Name": "Allred",
                        "I.D.": "Sabrina",
                        "Sex": 25094,
                        "Birth Date": "F",
                        "Age": "1978",
                        "Employee Type": 41.0,
                        "Employee": "Probation & Parole",
                        "Instructor": "[X]",
                        "Supervisor": "[ ]"
                    },
                    {
                        "Name": "Althaus",
                        "I.D.": "Terry L.",
                        "Sex": 28,
                        "Birth Date": "M",
                        "Age": "1960",
                        "Employee Type": 59.0,
                        "Employee": "Peace Officer",
                        "Instructor": "[X]",
                        "Supervisor": "[ ]"
                    },
                    {
                        "Name": "Altmiller",
                        "I.D.": "Jason D.",
                        "Sex": 24024,
                        "Birth Date": NaN,
                        "Age": NaN,
                        "Employee Type": NaN,
                        "Employee": "Peace Officer",
                        "Instructor": "[X]",
                        "Supervisor": "[ ]"
                    },
                    {
                        "Name": "Altschwager",
                        "I.D.": "Daniel T.",
                        "Sex": 20936,
                        "Birth Date": "M",
                        "Age": "-1983",
                        "Employee Type": 35.0,
                        "Employee": "Peace Officer",
                        "Instructor": "[X]",
                        "Supervisor": "[ ]"
                    }
                ]
            }
        ]
    },
    {
        "id": 2,
        "content": [
            {
                "type": "table",
                "content": [
                    {
                        "Name": "Amaro",
                        "I.D.": "Ishmael G.",
                        "Sex": 25336,
                        "Birth Date": "M",
                        "Age": "[X] 1995",
                        "Employee Type": "24",
                        "Employee": "Detention & Correction",
                        "Instructor": "[X]",
                        "Supervisor": "[ ]"
                    },
                    {
                        "Name": "Ames",
                        "I.D.": "Danny H.",
                        "Sex": 34,
                        "Birth Date": NaN,
                        "Age": NaN,
                        "Employee Type": "[X]",
                        "Employee": "Peace Officer",
                        "Instructor": "[X]",
                        "Supervisor": "[ ]"
                    },
                    {
                        "Name": "Ames",
                        "I.D.": "Joshua A.",
                        "Sex": 24710,
                        "Birth Date": "M",
                        "Age": "[ ] 1981",
                        "Employee Type": "38",
                        "Employee": "Peace Officer",
                        "Instructor": "[X]",
                        "Supervisor": "[ ]"
                    },
                    {
                        "Name": "Amundsen",
                        "I.D.": "Gregory M.",
                        "Sex": 2435,
                        "Birth Date": "M",
                        "Age": "[X] 1961",
                        "Employee Type": "58",
                        "Employee": "Peace Officer",
                        "Instructor": "[X]",
                        "Supervisor": "[ ]"
                    },
                    {
                        "Name": "Amundson",
                        "I.D.": "Daniel S.",
                        "Sex": 14908,
                        "Birth Date": "M",
                        "Age": "[ ] 1969",
                        "Employee Type": "50",
                        "Employee": "Peace Officer",
                        "Instructor": "[X]",
                        "Supervisor": "[ ]"
                    },
                    {
                        "Name": "Anderberg",
                        "I.D.": "Chad B.",
                        "Sex": 22675,
                        "Birth Date": "M",
                        "Age": "[ ] 1986",
                        "Employee Type": "33",
                        "Employee": "Peace Officer",
                        "Instructor": "[X]",
                        "Supervisor": "[ ]"
                    },
                    {
                        "Name": "Andersen",
                        "I.D.": "Dirk",
                        "Sex": 36,
                        "Birth Date": "M",
                        "Age": "[ ] 1957",
                        "Employee Type": "62",
                        "Employee": "Reserve",
                        "Instructor": "[X]",
                        "Supervisor": "[ ]"
                    },
                    {
                        "Name": "Andersen",
                        "I.D.": "Shad A.",
                        "Sex": 19490,
                        "Birth Date": "M",
                        "Age": "[ ] 1974",
                        "Employee Type": "45",
                        "Employee": "Peace Officer",
                        "Instructor": "[X]",
                        "Supervisor": "[ ]"
                    },
                    {
                        "Name": "Anderson",
                        "I.D.": "Adam S.",
                        "Sex": 25070,
                        "Birth Date": "M",
                        "Age": "[ ] 1983",
                        "Employee Type": "36",
                        "Employee": "Detention & Correction",
                        "Instructor": "[X]",
                        "Supervisor": "[ ]"
                    },
                    {
                        "Name": "Anderson",
                        "I.D.": "Bryan L.",
                        "Sex": 23954,
                        "Birth Date": "M",
                        "Age": "[ ] 1984",
                        "Employee Type": "35",
                        "Employee": "Peace Officer",
                        "Instructor": "[X]",
                        "Supervisor": "[ ]"
                    },
                    {
                        "Name": "Anderson",
                        "I.D.": "Cache",
                        "Sex": 21951,
                        "Birth Date": "M",
                        "Age": "[ ] 1982",
                        "Employee Type": "37",
                        "Employee": "Peace Officer",
                        "Instructor": "[X]",
                        "Supervisor": "[ ]"
                    },
                    {
                        "Name": "Anderson",
                        "I.D.": "Cactus J.",
                        "Sex": 21851,
                        "Birth Date": "M",
                        "Age": "[ ] 1980",
                        "Employee Type": "39",
                        "Employee": "Peace Officer",
                        "Instructor": "[X]",
                        "Supervisor": "[ ]"
                    },
                    {
                        "Name": "Anderson",
                        "I.D.": "Clint W.",
                        "Sex": 19254,
                        "Birth Date": "M",
                        "Age": "[ ] 1980",
                        "Employee Type": "39",
                        "Employee": "Peace Officer",
                        "Instructor": "[X]",
                        "Supervisor": "[ ]"
                    },
                    {
                        "Name": "Anderson",
                        "I.D.": "Codee R.",
                        "Sex": 19273,
                        "Birth Date": NaN,
                        "Age": "-1987",
                        "Employee Type": "31",
                        "Employee": "Reserve",
                        "Instructor": "[X]",
                        "Supervisor": "[ ]"
                    },
                    {
                        "Name": "Anderson",
                        "I.D.": "David A.",
                        "Sex": 14614,
                        "Birth Date": "M",
                        "Age": "[ ] -1964",
                        "Employee Type": "54",
                        "Employee": "Detention & Correction",
                        "Instructor": "[X]",
                        "Supervisor": "[ ]"
                    },
                    {
                        "Name": "Anderson",
                        "I.D.": "lan M.",
                        "Sex": 22250,
                        "Birth Date": "M",
                        "Age": "[ ] -1989",
                        "Employee Type": "29",
                        "Employee": "Peace Officer",
                        "Instructor": "[X]",
                        "Supervisor": "[ ]"
                    },
                    {
                        "Name": "Anderson",
                        "I.D.": "James R.",
                        "Sex": 13738,
                        "Birth Date": "M",
                        "Age": "-1971",
                        "Employee Type": "47",
                        "Employee": "Peace Officer",
                        "Instructor": "[X]",
                        "Supervisor": "[ ]"
                    },
                    {
                        "Name": "Anderson",
                        "I.D.": "Jonathan M.",
                        "Sex": 18722,
                        "Birth Date": "M",
                        "Age": "[ ] 1969",
                        "Employee Type": "50",
                        "Employee": "Peace Officer",
                        "Instructor": "[X]",
                        "Supervisor": "[ ]"
                    },
                    {
                        "Name": "Anderson",
                        "I.D.": "Joshua S.",
                        "Sex": 25301,
                        "Birth Date": "M",
                        "Age": "1994",
                        "Employee Type": "25",
                        "Employee": "Peace Officer",
                        "Instructor": "[X]",
                        "Supervisor": "[ ]"
                    },
                    {
                        "Name": "Anderson",
                        "I.D.": "Kent M.",
                        "Sex": 18466,
                        "Birth Date": "M",
                        "Age": "[ ] 1984",
                        "Employee Type": "35",
                        "Employee": "Peace Officer",
                        "Instructor": "[X]",
                        "Supervisor": "[ ]"
                    },
                    {
                        "Name": "Anderson",
                        "I.D.": "Lee R.",
                        "Sex": 7664,
                        "Birth Date": "M",
                        "Age": "[ ] 1972",
                        "Employee Type": "47",
                        "Employee": "Peace Officer",
                        "Instructor": "[X]",
                        "Supervisor": "[ ]"
                    },
                    {
                        "Name": "Anderson",
                        "I.D.": "Michael B.",
                        "Sex": 23290,
                        "Birth Date": "M",
                        "Age": "1985",
                        "Employee Type": "34",
                        "Employee": "Peace Officer",
                        "Instructor": "[X]",
                        "Supervisor": "[ ]"
                    },
                    {
                        "Name": "Anderson",
                        "I.D.": "Spencer P.",
                        "Sex": 9378,
                        "Birth Date": "M",
                        "Age": "1977",
                        "Employee Type": "42",
                        "Employee": "Peace Officer",
                        "Instructor": "[X]",
                        "Supervisor": "[ ]"
                    },
                    {
                        "Name": "Anderson",
                        "I.D.": "Steve F.",
                        "Sex": 13276,
                        "Birth Date": "M",
                        "Age": "1964",
                        "Employee Type": "55",
                        "Employee": "Detention & Correction",
                        "Instructor": "[X]",
                        "Supervisor": "[ ]"
                    },
                    {
                        "Name": "Andress",
                        "I.D.": "Robert W.",
                        "Sex": 19652,
                        "Birth Date": NaN,
                        "Age": NaN,
                        "Employee Type": NaN,
                        "Employee": "Peace Officer",
                        "Instructor": "[X]",
                        "Supervisor": "[ ]"
                    },
                    {
                        "Name": "Andrews",
                        "I.D.": "Justin C.",
                        "Sex": 20912,
                        "Birth Date": "M",
                        "Age": "-1988",
                        "Employee Type": "30",
                        "Employee": "Peace Officer",
                        "Instructor": "[X]",
                        "Supervisor": "[ ]"
                    },
                    {
                        "Name": "Anglin",
                        "I.D.": "Clint C.",
                        "Sex": 21081,
                        "Birth Date": "M",
                        "Age": "1978",
                        "Employee Type": "41",
                        "Employee": "Peace Officer",
                        "Instructor": "[X]",
                        "Supervisor": "[ ]"
                    },
                    {
                        "Name": "Anglin",
                        "I.D.": "Jarred G.",
                        "Sex": 20563,
                        "Birth Date": "M",
                        "Age": "1986",
                        "Employee Type": "33",
                        "Employee": "Peace Officer",
                        "Instructor": "[X]",
                        "Supervisor": "[ ]"
                    },
                    {
                        "Name": "Araujo",
                        "I.D.": "Christopher R.",
                        "Sex": 21405,
                        "Birth Date": "M",
                        "Age": "-1988",
                        "Employee Type": "30",
                        "Employee": "Peace Officer",
                        "Instructor": "[X]",
                        "Supervisor": "[ ]"
                    },
                    {
                        "Name": "Arca",
                        "I.D.": "Shelby M.",
                        "Sex": 25106,
                        "Birth Date": "F",
                        "Age": "1993",
                        "Employee Type": "26",
                        "Employee": "Detention & Correction",
                        "Instructor": "[X]",
                        "Supervisor": "[ ]"
                    },
                    {
                        "Name": "Arends",
                        "I.D.": "Linda N.",
                        "Sex": 19463,
                        "Birth Date": "F",
                        "Age": "-1958",
                        "Employee Type": "60",
                        "Employee": "Detention & Correction",
                        "Instructor": "[X]",
                        "Supervisor": "[ ]"
                    },
                    {
                        "Name": "Arlee",
                        "I.D.": "Travis L.",
                        "Sex": 24828,
                        "Birth Date": "M",
                        "Age": "1971",
                        "Employee Type": "48",
                        "Employee": "Peace Officer",
                        "Instructor": "[X]",
                        "Supervisor": "[ ]"
                    }
                ]
            }
        ]
    },
    {
        "id": 3,
        "content": [
            {
                "type": "table",
                "content": [
                    {
                        "Name": "Arment",
                        "I.D.": "Marc T.",
                        "Sex": 25133,
                        "Birth Date": "M",
                        "Age": "[X] 1982",
                        "Employee Type": 37,
                        "Employee": "Peace Officer",
                        "Instructor": "[X]",
                        "Supervisor": "[ ]"
                    },
                    {
                        "Name": "Armstrong",
                        "I.D.": "Barbara A.",
                        "Sex": 23185,
                        "Birth Date": "F",
                        "Age": "[X] 1981",
                        "Employee Type": 38,
                        "Employee": "Peace Officer",
                        "Instructor": "[X]",
                        "Supervisor": "[ ]"
                    },
                    {
                        "Name": "Armstrong",
                        "I.D.": "Donald",
                        "Sex": 20144,
                        "Birth Date": "M",
                        "Age": "1962",
                        "Employee Type": 57,
                        "Employee": "Detention & Correction",
                        "Instructor": "[X]",
                        "Supervisor": "[ ]"
                    },
                    {
                        "Name": "Armstrong",
                        "I.D.": "Robert J.",
                        "Sex": 6665,
                        "Birth Date": "M",
                        "Age": "1970",
                        "Employee Type": 49,
                        "Employee": "Peace Officer",
                        "Instructor": "[X]",
                        "Supervisor": "[ ]"
                    },
                    {
                        "Name": "Arneson",
                        "I.D.": "Jerod",
                        "Sex": 25385,
                        "Birth Date": "M",
                        "Age": "1993",
                        "Employee Type": 26,
                        "Employee": "Detention & Correction",
                        "Instructor": "[X]",
                        "Supervisor": "[ ]"
                    },
                    {
                        "Name": "Arneson",
                        "I.D.": "Kyle R.",
                        "Sex": 23417,
                        "Birth Date": "M",
                        "Age": "-1992",
                        "Employee Type": 26,
                        "Employee": "Detention & Correction",
                        "Instructor": "[X]",
                        "Supervisor": "[ ]"
                    },
                    {
                        "Name": "Arnett",
                        "I.D.": "Tracie",
                        "Sex": 25220,
                        "Birth Date": NaN,
                        "Age": "-1975",
                        "Employee Type": 43,
                        "Employee": "Detention & Correction",
                        "Instructor": "[X]",
                        "Supervisor": "[ ]"
                    },
                    {
                        "Name": "Arnold",
                        "I.D.": "Daniel T.",
                        "Sex": 19975,
                        "Birth Date": "M",
                        "Age": "1985",
                        "Employee Type": 34,
                        "Employee": "Peace Officer",
                        "Instructor": "[X]",
                        "Supervisor": "[ ]"
                    },
                    {
                        "Name": "Arnold",
                        "I.D.": "Jonathan",
                        "Sex": 23669,
                        "Birth Date": "M",
                        "Age": "[ ] 1989",
                        "Employee Type": 30,
                        "Employee": "Peace Officer",
                        "Instructor": "[X]",
                        "Supervisor": "[ ]"
                    },
                    {
                        "Name": "Asencio",
                        "I.D.": "Ben",
                        "Sex": 8807,
                        "Birth Date": "M",
                        "Age": "[ ] 1973",
                        "Employee Type": 46,
                        "Employee": "Peace Officer",
                        "Instructor": "[X]",
                        "Supervisor": "[ ]"
                    },
                    {
                        "Name": "Ashby",
                        "I.D.": "Steven E.",
                        "Sex": 19525,
                        "Birth Date": "M",
                        "Age": "[ ] 1967",
                        "Employee Type": 52,
                        "Employee": "Peace Officer",
                        "Instructor": "[X]",
                        "Supervisor": "[ ]"
                    },
                    {
                        "Name": "Atkins",
                        "I.D.": "Dustin L.",
                        "Sex": 20950,
                        "Birth Date": "M",
                        "Age": "[ ] 1979",
                        "Employee Type": 40,
                        "Employee": "Detention & Correction",
                        "Instructor": "[X]",
                        "Supervisor": "[ ]"
                    },
                    {
                        "Name": "Atkinson",
                        "I.D.": "Ann E.",
                        "Sex": 18567,
                        "Birth Date": "F",
                        "Age": "[ ] 1962",
                        "Employee Type": 57,
                        "Employee": "Detention & Correction",
                        "Instructor": "[X]",
                        "Supervisor": "[ ]"
                    },
                    {
                        "Name": "Atkinson Jr.",
                        "I.D.": "Michael T.",
                        "Sex": 7170,
                        "Birth Date": "M",
                        "Age": "[ ] 1973",
                        "Employee Type": 46,
                        "Employee": "Peace Officer",
                        "Instructor": "[X]",
                        "Supervisor": "[ ]"
                    },
                    {
                        "Name": "Atsbeha",
                        "I.D.": "Eayoall M.",
                        "Sex": 24420,
                        "Birth Date": "M",
                        "Age": "[ ] 1987",
                        "Employee Type": 32,
                        "Employee": "Detention & Correction",
                        "Instructor": "[X]",
                        "Supervisor": "[ ]"
                    },
                    {
                        "Name": "Auch",
                        "I.D.": "Jacob A.",
                        "Sex": 19106,
                        "Birth Date": "M",
                        "Age": "[ ] 1981",
                        "Employee Type": 38,
                        "Employee": "Peace Officer",
                        "Instructor": "[X]",
                        "Supervisor": "[ ]"
                    },
                    {
                        "Name": "Austin",
                        "I.D.": "Alicia M.",
                        "Sex": 18355,
                        "Birth Date": "F",
                        "Age": "1978",
                        "Employee Type": 41,
                        "Employee": "Peace Officer",
                        "Instructor": "[X]",
                        "Supervisor": "[ ]"
                    },
                    {
                        "Name": "Austin",
                        "I.D.": "John R.",
                        "Sex": 7163,
                        "Birth Date": "M",
                        "Age": "-1964",
                        "Employee Type": 54,
                        "Employee": "Peace Officer",
                        "Instructor": "[X]",
                        "Supervisor": "[ ]"
                    },
                    {
                        "Name": "Axelrod",
                        "I.D.": "Bryan J.",
                        "Sex": 23027,
                        "Birth Date": "M",
                        "Age": "1984",
                        "Employee Type": 35,
                        "Employee": "Peace Officer",
                        "Instructor": "[X]",
                        "Supervisor": "[ ]"
                    },
                    {
                        "Name": "Ayers",
                        "I.D.": "Brandon L.",
                        "Sex": 25583,
                        "Birth Date": "M",
                        "Age": "1992",
                        "Employee Type": 27,
                        "Employee": "Peace Officer",
                        "Instructor": "[X]",
                        "Supervisor": "[ ]"
                    },
                    {
                        "Name": "Ayers",
                        "I.D.": "Jeralyn",
                        "Sex": 11031,
                        "Birth Date": "F",
                        "Age": "-1961",
                        "Employee Type": 57,
                        "Employee": "Detention & Correction",
                        "Instructor": "[X]",
                        "Supervisor": "[ ]"
                    },
                    {
                        "Name": "Bach",
                        "I.D.": "Trinity L.",
                        "Sex": 23022,
                        "Birth Date": "F",
                        "Age": "1968",
                        "Employee Type": 51,
                        "Employee": "Detention & Correction",
                        "Instructor": "[X]",
                        "Supervisor": "[ ]"
                    },
                    {
                        "Name": "Baggs",
                        "I.D.": "David J.",
                        "Sex": 17559,
                        "Birth Date": "M",
                        "Age": "-1975",
                        "Employee Type": 43,
                        "Employee": "Peace Officer",
                        "Instructor": "[X]",
                        "Supervisor": "[ ]"
                    },
                    {
                        "Name": "Bagnoli",
                        "I.D.": "Colton J.",
                        "Sex": 23146,
                        "Birth Date": "M",
                        "Age": "1983",
                        "Employee Type": 36,
                        "Employee": "Peace Officer",
                        "Instructor": "[X]",
                        "Supervisor": "[ ]"
                    },
                    {
                        "Name": "Baiamonte",
                        "I.D.": "Stephen",
                        "Sex": 2355,
                        "Birth Date": "M",
                        "Age": "-1967",
                        "Employee Type": 51,
                        "Employee": "Reserve",
                        "Instructor": "[X]",
                        "Supervisor": "[ ]"
                    },
                    {
                        "Name": "Bailey",
                        "I.D.": "Cory A.",
                        "Sex": 7358,
                        "Birth Date": "M",
                        "Age": "-1971",
                        "Employee Type": 47,
                        "Employee": "Peace Officer",
                        "Instructor": "[X]",
                        "Supervisor": "[ ]"
                    },
                    {
                        "Name": "Bailey",
                        "I.D.": "Dunny W.",
                        "Sex": 17225,
                        "Birth Date": NaN,
                        "Age": "-1975",
                        "Employee Type": 43,
                        "Employee": "Detention & Correction",
                        "Instructor": "[X]",
                        "Supervisor": "[ ]"
                    },
                    {
                        "Name": "Bailey",
                        "I.D.": "James A.",
                        "Sex": 17111,
                        "Birth Date": NaN,
                        "Age": "1975",
                        "Employee Type": 44,
                        "Employee": "Peace Officer",
                        "Instructor": "[X]",
                        "Supervisor": "[ ]"
                    },
                    {
                        "Name": "Bailey",
                        "I.D.": "James S.",
                        "Sex": 12458,
                        "Birth Date": "M",
                        "Age": "1962",
                        "Employee Type": 57,
                        "Employee": "Detention & Correction",
                        "Instructor": "[X]",
                        "Supervisor": "[ ]"
                    },
                    {
                        "Name": "Bain",
                        "I.D.": "Dennis A.",
                        "Sex": 21271,
                        "Birth Date": "M",
                        "Age": "[ ] 1977",
                        "Employee Type": 42,
                        "Employee": "Peace Officer",
                        "Instructor": "[X]",
                        "Supervisor": "[ ]"
                    },
                    {
                        "Name": "Baken",
                        "I.D.": "Nicholas",
                        "Sex": 25410,
                        "Birth Date": "M",
                        "Age": "[ ] 1994",
                        "Employee Type": 25,
                        "Employee": "Detention & Correction",
                        "Instructor": "[X]",
                        "Supervisor": "[ ]"
                    },
                    {
                        "Name": "Baker",
                        "I.D.": "Christopher J.",
                        "Sex": 18409,
                        "Birth Date": "M",
                        "Age": "1974",
                        "Employee Type": 45,
                        "Employee": "Peace Officer",
                        "Instructor": "[X]",
                        "Supervisor": "[ ]"
                    }
                ]
            }
        ]
    },
    {
        "id": 4,
        "content": [
            {
                "type": "table",
                "content": [
                    {
                        "Name": "Baker",
                        "I.D.": "Guy A.",
                        "Sex": 2170,
                        "Birth Date": "M",
                        "Age": "[X] 1968",
                        "Employee Type": 51,
                        "Employee": "Peace Officer",
                        "Instructor": "[X]",
                        "Supervisor": "[ ]"
                    },
                    {
                        "Name": "Baker",
                        "I.D.": "Jason",
                        "Sex": 20803,
                        "Birth Date": "M",
                        "Age": "[X] -1971",
                        "Employee Type": 47,
                        "Employee": "Peace Officer",
                        "Instructor": "[X]",
                        "Supervisor": "[ ]"
                    },
                    {
                        "Name": "Baker",
                        "I.D.": "Rae M.",
                        "Sex": 21193,
                        "Birth Date": "F",
                        "Age": "1967",
                        "Employee Type": 52,
                        "Employee": "Probation & Parole",
                        "Instructor": "[X]",
                        "Supervisor": "[ ]"
                    },
                    {
                        "Name": "Balis",
                        "I.D.": "Bradford A.",
                        "Sex": 22324,
                        "Birth Date": "M",
                        "Age": "1987",
                        "Employee Type": 32,
                        "Employee": "Peace Officer",
                        "Instructor": "[X]",
                        "Supervisor": "[ ]"
                    },
                    {
                        "Name": "Ball",
                        "I.D.": "Christopher L.",
                        "Sex": 24117,
                        "Birth Date": "M",
                        "Age": "[ ] 1990",
                        "Employee Type": 29,
                        "Employee": "Detention & Correction",
                        "Instructor": "[X]",
                        "Supervisor": "[ ]"
                    },
                    {
                        "Name": "Baltezar",
                        "I.D.": "Beau C.",
                        "Sex": 20921,
                        "Birth Date": "M",
                        "Age": "1988",
                        "Employee Type": 31,
                        "Employee": "Detention & Correction",
                        "Instructor": "[X]",
                        "Supervisor": "[ ]"
                    },
                    {
                        "Name": "Barbao",
                        "I.D.": "Harlee I.",
                        "Sex": 23944,
                        "Birth Date": "M",
                        "Age": "1992",
                        "Employee Type": 27,
                        "Employee": "Peace Officer",
                        "Instructor": "[X]",
                        "Supervisor": "[ ]"
                    },
                    {
                        "Name": "Barbera",
                        "I.D.": "Andrew J.",
                        "Sex": 25525,
                        "Birth Date": "M",
                        "Age": "[X] 1983",
                        "Employee Type": 36,
                        "Employee": "Peace Officer",
                        "Instructor": "[X]",
                        "Supervisor": "[ ]"
                    },
                    {
                        "Name": "Barce",
                        "I.D.": "Austin",
                        "Sex": 25262,
                        "Birth Date": "M",
                        "Age": "-1992",
                        "Employee Type": 26,
                        "Employee": "Detention & Correction",
                        "Instructor": "[X]",
                        "Supervisor": "[ ]"
                    },
                    {
                        "Name": "Barclay",
                        "I.D.": "Steven B.",
                        "Sex": 5854,
                        "Birth Date": NaN,
                        "Age": "1969",
                        "Employee Type": 50,
                        "Employee": "Peace Officer",
                        "Instructor": "[X]",
                        "Supervisor": "[ ]"
                    },
                    {
                        "Name": "Bardwell",
                        "I.D.": "Allen G.",
                        "Sex": 2205,
                        "Birth Date": "M",
                        "Age": "-1956",
                        "Employee Type": 62,
                        "Employee": "Peace Officer",
                        "Instructor": "[X]",
                        "Supervisor": "[ ]"
                    },
                    {
                        "Name": "Bare",
                        "I.D.": "Bryce",
                        "Sex": 23344,
                        "Birth Date": "M",
                        "Age": "1992",
                        "Employee Type": 27,
                        "Employee": "Peace Officer",
                        "Instructor": "[X]",
                        "Supervisor": "[ ]"
                    },
                    {
                        "Name": "Barkell",
                        "I.D.": "Tim F.",
                        "Sex": 2178,
                        "Birth Date": "M",
                        "Age": "[ ] 1962",
                        "Employee Type": 57,
                        "Employee": "Peace Officer",
                        "Instructor": "[X]",
                        "Supervisor": "[ ]"
                    },
                    {
                        "Name": "Barkus",
                        "I.D.": "Jason A.",
                        "Sex": 18592,
                        "Birth Date": "M",
                        "Age": "1971",
                        "Employee Type": 48,
                        "Employee": "Peace Officer",
                        "Instructor": "[X]",
                        "Supervisor": "[ ]"
                    },
                    {
                        "Name": "Barnes",
                        "I.D.": "Timothy C.",
                        "Sex": 14393,
                        "Birth Date": "M",
                        "Age": "[ ] 1962",
                        "Employee Type": 57,
                        "Employee": "Peace Officer",
                        "Instructor": "[X]",
                        "Supervisor": "[ ]"
                    },
                    {
                        "Name": "Barnt",
                        "I.D.": "James J.",
                        "Sex": 17399,
                        "Birth Date": "M",
                        "Age": "[ ] 1977",
                        "Employee Type": 42,
                        "Employee": "Detention & Correction",
                        "Instructor": "[X]",
                        "Supervisor": "[ ]"
                    },
                    {
                        "Name": "Barrett",
                        "I.D.": "Anthony",
                        "Sex": 25112,
                        "Birth Date": "M",
                        "Age": "[ ] 1963",
                        "Employee Type": 56,
                        "Employee": "Probation & Parole",
                        "Instructor": "[X]",
                        "Supervisor": "[ ]"
                    },
                    {
                        "Name": "Barrett",
                        "I.D.": "Michael P.",
                        "Sex": 23109,
                        "Birth Date": "M",
                        "Age": "[ ] 1987",
                        "Employee Type": 32,
                        "Employee": "Reserve",
                        "Instructor": "[X]",
                        "Supervisor": "[ ]"
                    },
                    {
                        "Name": "Barry",
                        "I.D.": "Chan A.",
                        "Sex": 19972,
                        "Birth Date": "M",
                        "Age": "[ ] 1975",
                        "Employee Type": 44,
                        "Employee": "Peace Officer",
                        "Instructor": "[X]",
                        "Supervisor": "[ ]"
                    },
                    {
                        "Name": "Barsness",
                        "I.D.": "Kyle P.",
                        "Sex": 19386,
                        "Birth Date": "M",
                        "Age": "[ ] 1980",
                        "Employee Type": 39,
                        "Employee": "Peace Officer",
                        "Instructor": "[X]",
                        "Supervisor": "[ ]"
                    },
                    {
                        "Name": "Barstad",
                        "I.D.": "Bruce E.",
                        "Sex": 99,
                        "Birth Date": "M",
                        "Age": "1966",
                        "Employee Type": 53,
                        "Employee": "Probation & Parole",
                        "Instructor": "[X]",
                        "Supervisor": "[ ]"
                    },
                    {
                        "Name": "Barthel",
                        "I.D.": "Jon J.",
                        "Sex": 14630,
                        "Birth Date": "M",
                        "Age": "-1974",
                        "Employee Type": 44,
                        "Employee": "Detention & Correction",
                        "Instructor": "[X]",
                        "Supervisor": "[ ]"
                    },
                    {
                        "Name": "Barthel",
                        "I.D.": "Michael J.",
                        "Sex": 100,
                        "Birth Date": "M",
                        "Age": "-1964",
                        "Employee Type": 54,
                        "Employee": "Probation & Parole",
                        "Instructor": "[X]",
                        "Supervisor": "[ ]"
                    },
                    {
                        "Name": "Barton",
                        "I.D.": "Andrew K.",
                        "Sex": 21997,
                        "Birth Date": "M",
                        "Age": "1985",
                        "Employee Type": 34,
                        "Employee": "Peace Officer",
                        "Instructor": "[X]",
                        "Supervisor": "[ ]"
                    },
                    {
                        "Name": "Bartos",
                        "I.D.": "Charles D.",
                        "Sex": 6307,
                        "Birth Date": "M",
                        "Age": "1966",
                        "Employee Type": 53,
                        "Employee": "Peace Officer",
                        "Instructor": "[X]",
                        "Supervisor": "[ ]"
                    },
                    {
                        "Name": "Barzen",
                        "I.D.": "Jake",
                        "Sex": 25486,
                        "Birth Date": "M",
                        "Age": "-1994",
                        "Employee Type": 24,
                        "Employee": "Peace Officer",
                        "Instructor": "[X]",
                        "Supervisor": "[ ]"
                    },
                    {
                        "Name": "Bauer",
                        "I.D.": "Dustin L.",
                        "Sex": 22217,
                        "Birth Date": "M",
                        "Age": "1989",
                        "Employee Type": 30,
                        "Employee": "Detention & Correction",
                        "Instructor": "[X]",
                        "Supervisor": "[ ]"
                    },
                    {
                        "Name": "Baugatz Jr.",
                        "I.D.": "John A.",
                        "Sex": 7011,
                        "Birth Date": "M",
                        "Age": "-1964",
                        "Employee Type": 54,
                        "Employee": "Detention & Correction",
                        "Instructor": "[X]",
                        "Supervisor": "[ ]"
                    },
                    {
                        "Name": "Baukema",
                        "I.D.": "Toman L.",
                        "Sex": 6667,
                        "Birth Date": "M",
                        "Age": "1969",
                        "Employee Type": 50,
                        "Employee": "Peace Officer",
                        "Instructor": "[X]",
                        "Supervisor": "[ ]"
                    },
                    {
                        "Name": "Baum",
                        "I.D.": "Craig A.",
                        "Sex": 6047,
                        "Birth Date": "M",
                        "Age": "1971",
                        "Employee Type": 48,
                        "Employee": "Peace Officer",
                        "Instructor": "[X]",
                        "Supervisor": "[ ]"
                    },
                    {
                        "Name": "Baum",
                        "I.D.": "Denise K.",
                        "Sex": 8322,
                        "Birth Date": "F",
                        "Age": "-1967",
                        "Employee Type": 51,
                        "Employee": "Peace Officer",
                        "Instructor": "[X]",
                        "Supervisor": "[ ]"
                    },
                    {
                        "Name": "Baum",
                        "I.D.": "Michael J.",
                        "Sex": 23317,
                        "Birth Date": "M",
                        "Age": "1988",
                        "Employee Type": 31,
                        "Employee": "Peace Officer",
                        "Instructor": "[X]",
                        "Supervisor": "[ ]"
                    }
                ]
            }
        ]
    },
    {
        "id": 5,
        "content": [
            {
                "type": "table",
                "content": [
                    {
                        "Name": "Baumann",
                        "I.D.": "Eric A.",
                        "Sex": 8665,
                        "Birth Date": "M",
                        "Age": "[X] -1974",
                        "Employee Type": 44.0,
                        "Employee": "Peace Officer",
                        "Instructor": "[X]",
                        "Supervisor": "[ ]"
                    },
                    {
                        "Name": "Baxter",
                        "I.D.": "Jayson B.",
                        "Sex": 16490,
                        "Birth Date": "M",
                        "Age": "[X] 1970",
                        "Employee Type": 49.0,
                        "Employee": "Probation & Parole",
                        "Instructor": "[X]",
                        "Supervisor": "[ ]"
                    },
                    {
                        "Name": "Bear Medicine",
                        "I.D.": "Doyle L.",
                        "Sex": 24354,
                        "Birth Date": "M",
                        "Age": "1980",
                        "Employee Type": 39.0,
                        "Employee": "Peace Officer",
                        "Instructor": "[X]",
                        "Supervisor": "[ ]"
                    },
                    {
                        "Name": "Beard",
                        "I.D.": "Brenton A.",
                        "Sex": 24086,
                        "Birth Date": "M",
                        "Age": "1992",
                        "Employee Type": 27.0,
                        "Employee": "Peace Officer",
                        "Instructor": "[X]",
                        "Supervisor": "[ ]"
                    },
                    {
                        "Name": "Beasley",
                        "I.D.": "Daniel L.",
                        "Sex": 23062,
                        "Birth Date": "M",
                        "Age": "1981",
                        "Employee Type": 38.0,
                        "Employee": "Detention & Correction",
                        "Instructor": "[X]",
                        "Supervisor": "[ ]"
                    },
                    {
                        "Name": "Bebbington",
                        "I.D.": "Brian S.",
                        "Sex": 19543,
                        "Birth Date": "M",
                        "Age": "[ ] 1972",
                        "Employee Type": 47.0,
                        "Employee": "Peace Officer",
                        "Instructor": "[X]",
                        "Supervisor": "[ ]"
                    },
                    {
                        "Name": "Beccari",
                        "I.D.": "Kathleen M.",
                        "Sex": 10765,
                        "Birth Date": "F",
                        "Age": "[ ] 1961",
                        "Employee Type": 58.0,
                        "Employee": "Probation & Parole",
                        "Instructor": "[X]",
                        "Supervisor": "[ ]"
                    },
                    {
                        "Name": "Bechtold",
                        "I.D.": "Terry L.",
                        "Sex": 108,
                        "Birth Date": "M",
                        "Age": "[ ] 1959",
                        "Employee Type": 60.0,
                        "Employee": "Peace Officer",
                        "Instructor": "[X]",
                        "Supervisor": "[ ]"
                    },
                    {
                        "Name": "Beck",
                        "I.D.": "Benjamin T.",
                        "Sex": 21082,
                        "Birth Date": "M",
                        "Age": "[ ] 1988",
                        "Employee Type": 31.0,
                        "Employee": "Peace Officer",
                        "Instructor": "[X]",
                        "Supervisor": "[ ]"
                    },
                    {
                        "Name": "Beck",
                        "I.D.": "James J.",
                        "Sex": 22102,
                        "Birth Date": "M",
                        "Age": "1991",
                        "Employee Type": 28.0,
                        "Employee": "Peace Officer",
                        "Instructor": "[X]",
                        "Supervisor": "[ ]"
                    },
                    {
                        "Name": "Becker",
                        "I.D.": "Thomas",
                        "Sex": 25626,
                        "Birth Date": "M",
                        "Age": "-1984",
                        "Employee Type": 34.0,
                        "Employee": "Detention & Correction",
                        "Instructor": "[X]",
                        "Supervisor": "[ ]"
                    },
                    {
                        "Name": "Beckett",
                        "I.D.": "Jace A.",
                        "Sex": 22375,
                        "Birth Date": NaN,
                        "Age": "1992",
                        "Employee Type": 27.0,
                        "Employee": "Peace Officer",
                        "Instructor": "[X]",
                        "Supervisor": "[ ]"
                    },
                    {
                        "Name": "Beckwith",
                        "I.D.": "Carl F.",
                        "Sex": 7622,
                        "Birth Date": "M",
                        "Age": "-1940",
                        "Employee Type": 78.0,
                        "Employee": "Reserve",
                        "Instructor": "[X]",
                        "Supervisor": "[ ]"
                    },
                    {
                        "Name": "Bedford",
                        "I.D.": "John R.",
                        "Sex": 1902,
                        "Birth Date": "M",
                        "Age": "1961",
                        "Employee Type": 58.0,
                        "Employee": "Peace Officer",
                        "Instructor": "[X]",
                        "Supervisor": "[ ]"
                    },
                    {
                        "Name": "Beechie",
                        "I.D.": "Michael B.",
                        "Sex": 23596,
                        "Birth Date": "M",
                        "Age": "[ ] 1988",
                        "Employee Type": 31.0,
                        "Employee": "Peace Officer",
                        "Instructor": "[X]",
                        "Supervisor": "[ ]"
                    },
                    {
                        "Name": "Beecroft",
                        "I.D.": "Jeffery D.",
                        "Sex": 2095,
                        "Birth Date": "M",
                        "Age": "[ ] 1962",
                        "Employee Type": 57.0,
                        "Employee": "Peace Officer",
                        "Instructor": "[X]",
                        "Supervisor": "[ ]"
                    },
                    {
                        "Name": "Beehler",
                        "I.D.": "Anton J.",
                        "Sex": 9746,
                        "Birth Date": "M",
                        "Age": "1967",
                        "Employee Type": 52.0,
                        "Employee": "Peace Officer",
                        "Instructor": "[X]",
                        "Supervisor": "[ ]"
                    },
                    {
                        "Name": "Beeson Jr.",
                        "I.D.": "Myron",
                        "Sex": 25744,
                        "Birth Date": "M",
                        "Age": "[ ] 1979",
                        "Employee Type": 40.0,
                        "Employee": "Detention & Correction",
                        "Instructor": "[X]",
                        "Supervisor": "[ ]"
                    },
                    {
                        "Name": "Belcourt",
                        "I.D.": "Jalin C.",
                        "Sex": 24131,
                        "Birth Date": "M",
                        "Age": "1994",
                        "Employee Type": 25.0,
                        "Employee": "Peace Officer",
                        "Instructor": "[X]",
                        "Supervisor": "[ ]"
                    },
                    {
                        "Name": "Belford",
                        "I.D.": "Austin J.",
                        "Sex": 25558,
                        "Birth Date": NaN,
                        "Age": NaN,
                        "Employee Type": NaN,
                        "Employee": "Peace Officer",
                        "Instructor": "[X]",
                        "Supervisor": "[ ]"
                    },
                    {
                        "Name": "Bell",
                        "I.D.": "Donald R.",
                        "Sex": 5860,
                        "Birth Date": "M",
                        "Age": "-1958",
                        "Employee Type": 60.0,
                        "Employee": "Peace Officer",
                        "Instructor": "[X]",
                        "Supervisor": "[ ]"
                    },
                    {
                        "Name": "Bellusci",
                        "I.D.": "George E.",
                        "Sex": 23418,
                        "Birth Date": "M",
                        "Age": "1970",
                        "Employee Type": 49.0,
                        "Employee": "Detention & Correction",
                        "Instructor": "[X]",
                        "Supervisor": "[ ]"
                    },
                    {
                        "Name": "Bellusci",
                        "I.D.": "William W.",
                        "Sex": 118,
                        "Birth Date": "M",
                        "Age": "-1953",
                        "Employee Type": 65.0,
                        "Employee": "Probation & Parole",
                        "Instructor": "[X]",
                        "Supervisor": "[ ]"
                    },
                    {
                        "Name": "Bemis",
                        "I.D.": "Christopher W.",
                        "Sex": 6284,
                        "Birth Date": "M",
                        "Age": "-1964",
                        "Employee Type": 54.0,
                        "Employee": "Detention & Correction",
                        "Instructor": "[X]",
                        "Supervisor": "[ ]"
                    },
                    {
                        "Name": "Bender Jr.",
                        "I.D.": "Robert R.",
                        "Sex": 9665,
                        "Birth Date": "M",
                        "Age": "1978",
                        "Employee Type": 41.0,
                        "Employee": "Peace Officer",
                        "Instructor": "[X]",
                        "Supervisor": "[ ]"
                    },
                    {
                        "Name": "Bennett",
                        "I.D.": "Bryan R.",
                        "Sex": 23948,
                        "Birth Date": "M",
                        "Age": "1978",
                        "Employee Type": 41.0,
                        "Employee": "Peace Officer",
                        "Instructor": "[X]",
                        "Supervisor": "[ ]"
                    },
                    {
                        "Name": "Bennett",
                        "I.D.": "Scott F.",
                        "Sex": 13814,
                        "Birth Date": "M",
                        "Age": "1962",
                        "Employee Type": 57.0,
                        "Employee": "Peace Officer",
                        "Instructor": "[X]",
                        "Supervisor": "[ ]"
                    },
                    {
                        "Name": "Benson",
                        "I.D.": "Christopher J.",
                        "Sex": 24072,
                        "Birth Date": "M",
                        "Age": "-1981",
                        "Employee Type": 37.0,
                        "Employee": "Peace Officer",
                        "Instructor": "[X]",
                        "Supervisor": "[ ]"
                    },
                    {
                        "Name": "Benson",
                        "I.D.": "Michael S.",
                        "Sex": 127,
                        "Birth Date": "M",
                        "Age": "1965",
                        "Employee Type": 54.0,
                        "Employee": "Peace Officer",
                        "Instructor": "[X]",
                        "Supervisor": "[ ]"
                    },
                    {
                        "Name": "Benz",
                        "I.D.": "Britney B.",
                        "Sex": 24165,
                        "Birth Date": "F",
                        "Age": "1991",
                        "Employee Type": 28.0,
                        "Employee": "Peace Officer",
                        "Instructor": "[X]",
                        "Supervisor": "[ ]"
                    },
                    {
                        "Name": "Berg",
                        "I.D.": "Shannon",
                        "Sex": 25666,
                        "Birth Date": "F",
                        "Age": "1988",
                        "Employee Type": 31.0,
                        "Employee": "Probation & Parole",
                        "Instructor": "[X]",
                        "Supervisor": "[ ]"
                    },
                    {
                        "Name": "Berger",
                        "I.D.": "Brian P.",
                        "Sex": 21900,
                        "Birth Date": "M",
                        "Age": "-1985",
                        "Employee Type": 33.0,
                        "Employee": "Peace Officer",
                        "Instructor": "[X]",
                        "Supervisor": "[ ]"
                    }
                ]
            }
        ]
    }
]